mtoatools/__init__.py
mtoatools/api.py
mtoatools/hdr.py
mtoatools/menus.py
mtoatools/models.py
mtoatools/patches.py
mtoatools/plugins.py
mtoatools/utils.py
mtoatools/packages/__init__.py
mtoatools/packages/yaml/__init__.py
mtoatools/packages/yaml/composer.py
mtoatools/packages/yaml/constructor.py
mtoatools/packages/yaml/cyaml.py
mtoatools/packages/yaml/dumper.py
mtoatools/packages/yaml/emitter.py
mtoatools/packages/yaml/error.py
mtoatools/packages/yaml/events.py
mtoatools/packages/yaml/loader.py
mtoatools/packages/yaml/nodes.py
mtoatools/packages/yaml/parser.py
mtoatools/packages/yaml/reader.py
mtoatools/packages/yaml/representer.py
mtoatools/packages/yaml/resolver.py
mtoatools/packages/yaml/scanner.py
mtoatools/packages/yaml/serializer.py
mtoatools/packages/yaml/tokens.py
mtoatools/shelf/__init__.py
mtoatools/shelf/mtoatools_docs.png
mtoatools/shelf/mtoatools_docs_1x1.png
mtoatools/shelf/mtoatools_hdrig.png
mtoatools/shelf/mtoatools_hdrig_1x1.png
mtoatools/shelf/mtoatools_mattes.png
mtoatools/shelf/mtoatools_mattes_1x1.png
mtoatools/shelf/mtoatools_patches.png
mtoatools/shelf/mtoatools_patches_1x1.png
mtoatools/ui/__init__.py
mtoatools/ui/controllers.py
mtoatools/ui/dialogs.py
mtoatools/ui/style.css
mtoatools/ui/utils.py
mtoatools/ui/icons/delete.png
mtoatools/ui/icons/delete_pressed.png
mtoatools/ui/icons/help.png
mtoatools/ui/icons/icon.png
mtoatools/ui/icons/plus.png
mtoatools/ui/icons/plus_pressed.png
mtoatools/ui/icons/refresh.png
mtoatools/ui/icons/refresh_pressed.png
mtoatools-0.5.3.dist-info/METADATA
mtoatools-0.5.3.dist-info/RECORD
mtoatools-0.5.3.dist-info/WHEEL
mtoatools-0.5.3.dist-info/top_level.txt
